codon/__init__.py
codon/cli.py
codon/clock.py
codon/jsd.py
codon/masterslave.py
codon/ml.py
codon/mong.py
codon/monglog.py
codon/nest.py
codon/omega.py
codon/scipy_optimize.py
codon/selection.py
codon/timedec.py
codon/toposort.py
codon/util.py
codon-0.0.1.data/scripts/consume.py
codon-0.0.1.data/scripts/map_collection.py
codon-0.0.1.data/scripts/map_collection_slowly.py
codon-0.0.1.dist-info/DESCRIPTION.rst
codon-0.0.1.dist-info/entry_points.txt
codon-0.0.1.dist-info/METADATA
codon-0.0.1.dist-info/metadata.json
codon-0.0.1.dist-info/RECORD
codon-0.0.1.dist-info/top_level.txt
codon-0.0.1.dist-info/WHEEL
